MANIFEST.in
hr_employee_view.xml
setup.py
./__init__.py
./__openerp__.py
./hr_employee.py
i18n/cs.po
i18n/de.po
i18n/es.po
i18n/fr.po
i18n/hr.po
i18n/hu.po
i18n/lt.po
i18n/mk.po
i18n/nl.po
i18n/pl.po
i18n/portal_hr_employees.pot
i18n/pt.po
i18n/pt_BR.po
i18n/ro.po
i18n/sl.po
i18n/th.po
i18n/tr.po
i18n/zh_CN.po
openerp_portal_hr_employees.egg-info/PKG-INFO
openerp_portal_hr_employees.egg-info/SOURCES.txt
openerp_portal_hr_employees.egg-info/dependency_links.txt
openerp_portal_hr_employees.egg-info/requires.txt
openerp_portal_hr_employees.egg-info/top_level.txt
security/ir.model.access.csv